melodi/__init__.py
melodi/base_client.py
melodi/exceptions.py
melodi/logging.py
melodi/melodi_client.py
melodi/feedback/__init__.py
melodi/feedback/data_models.py
melodi/feedback/feedback_client.py
melodi/intents/__init__.py
melodi/intents/data_models.py
melodi/intents/intents_client.py
melodi/issues/__init__.py
melodi/issues/data_models.py
melodi/issues/issues_client.py
melodi/messages/__init__.py
melodi/messages/data_models.py
melodi/messages/messages_client.py
melodi/projects/__init__.py
melodi/projects/data_models.py
melodi/projects/projects_client.py
melodi/threads/__init__.py
melodi/threads/data_models.py
melodi/threads/threads_client.py
melodi/user_internal_for_project/__init__.py
melodi/user_internal_for_project/data_models.py
melodi/user_internal_for_project/user_internal_for_project_client.py
melodi/user_segment_types/__init__.py
melodi/user_segment_types/data_models.py
melodi/user_segment_types/user_segment_types_client.py
melodi/users/__init__.py
melodi/users/data_models.py
melodi/users/user_client.py
melodi/utils/__init__.py
melodi/utils/openai.py
melodi/utils/openai_nonstream_extractor.py
melodi/utils/openai_prompt_parser.py
melodi/utils/openai_stream_generator.py
melodi/utils/openai_utils.py
melodi/utils/utils.py
test/__init__.py
test/utils/__init__.py
test/utils/test_async_live.py
test/utils/test_live.py
test/utils/test_openai_nonstream_extractor.py
test/utils/test_openai_prompt_parser.py
test/utils/test_openai_stream_generator.py
melodi-0.2.0.dist-info/METADATA
melodi-0.2.0.dist-info/WHEEL
melodi-0.2.0.dist-info/top_level.txt
melodi-0.2.0.dist-info/RECORD
