Metadata-Version: 2.4
Name: melodi
Version: 0.2.0
Summary: Helper functions for Melodi - DEPRECATED
Author: Melodi Ltd
Author-email: info@melodi.fyi
Keywords: melodi
Requires-Dist: requests
Requires-Dist: pydantic
Requires-Dist: email-validator
Dynamic: author
Dynamic: author-email
Dynamic: description
Dynamic: description-content-type
Dynamic: keywords
Dynamic: requires-dist
Dynamic: summary
